affine/__init__.py
affine/collection.py
affine/query.py
affine/engine/__init__.py
affine/engine/base.py
affine/engine/local.py
affine/engine/pinecone.py
affine/engine/qdrant.py
affine/engine/weaviate.py
affine_vectordb-0.1.0.dist-info/METADATA
affine_vectordb-0.1.0.dist-info/WHEEL
affine_vectordb-0.1.0.dist-info/top_level.txt
affine_vectordb-0.1.0.dist-info/RECORD
