Metadata-Version: 2.1
Name: affine-vectordb
Version: 0.1.0
Summary: A unified interface for vector databases
Requires-Python: >=3.8
Requires-Dist: typing-extensions
Requires-Dist: numpy
Provides-Extra: dev
Requires-Dist: setuptools-scm ; extra == 'dev'
Requires-Dist: pre-commit ; extra == 'dev'
Provides-Extra: pinecone
Requires-Dist: pinecone-client ; extra == 'pinecone'
Provides-Extra: qdrant
Requires-Dist: qdrant-client ; extra == 'qdrant'
Provides-Extra: test
Requires-Dist: pytest ; extra == 'test'
Requires-Dist: coverage ; extra == 'test'
Provides-Extra: weaviate
Requires-Dist: weaviate-client >=4.0.0 ; extra == 'weaviate'
